MANIFEST.in
README.md
README.rst
setup.py
fast5purge/__init__.py
fast5purge/fast5purge.py
fast5purge/version.py
fast5purge.egg-info/PKG-INFO
fast5purge.egg-info/SOURCES.txt
fast5purge.egg-info/dependency_links.txt
fast5purge.egg-info/entry_points.txt
fast5purge.egg-info/requires.txt
fast5purge.egg-info/top_level.txt