Metadata-Version: 2.1
Name: fast5purge
Version: 0.2.0
Summary: Remove sensible content from a fast5 file or directory
Home-page: https://github.com/wdecoster/fast5purge
Author: Wouter De Coster
Author-email: decosterwouter@gmail.com
License: MIT
Keywords: nanopore
Platform: UNKNOWN
Classifier: Development Status :: 4 - Beta
Classifier: Intended Audience :: Science/Research
Classifier: Topic :: Scientific/Engineering :: Bio-Informatics
Classifier: License :: OSI Approved :: MIT License
Classifier: Programming Language :: Python :: 3
Classifier: Programming Language :: Python :: 3.3
Classifier: Programming Language :: Python :: 3.4
Classifier: Programming Language :: Python :: 3.5
Requires-Python: >=3
